<?xml version="1.0" encoding="UTF-8" standalone="no"?>
<pack>
    <sprite atlasID="0" default="0" defaultAnimation="0" desc="" height="50" id="1" name="ACTOR" shared="false" width="50">
        <anim across="1" down="1" durations="100" height="50" id="0" loop="true" name="Animation 0" numframes="1" originx="25" originy="25" sync="false" width="50">
            <poly data="4,0,0,50,0,50,50,0,50" density="0.1" fric="0.2" gid="-1000" id="0" name="Animation 0" rest="0.0" sensor="false"/>
        </anim>
    </sprite>
    <actor adamp="0.0" ascale="true" atlasID="0" bodytype="2" continuous="true" desc="" eventsnippetid="1" fixedrot="false" fric="0.2" gid="3" id="0" ignoreg="false" inertia="1.0" ldamp="0.0" lw="false" mass="1.0" name="ACTOR" oid="-1" pausable="true" rest="0.0" shared="false" sprite="1" static="false">
        <snippets/>
    </actor>
    <tileset across="1" atlasID="0" desc="" down="1" id="2" name="Green Tiles" oid="-1" shared="false" th="32" tw="32">
        <tile collision="1" data="" durations="100" frames="0" id="0" order="-1"/>
    </tileset>
</pack>
